eis1600/__init__.py
eis1600/bio/__init__.py
eis1600/bio/md_to_bio.py
eis1600/bio/prepare_training_data.py
eis1600/bio/q_tags_to_bio.py
eis1600/bio/topo_tags_to_bio.py
eis1600/corpus_analysis/__init__.py
eis1600/corpus_analysis/analyse_all_on_cluster.py
eis1600/corpus_analysis/analyse_text.py
eis1600/corpus_analysis/miu_methods.py
eis1600/corpus_analysis/text_methods.py
eis1600/dates/Date.py
eis1600/dates/Month.py
eis1600/dates/__init__.py
eis1600/dates/date_methods.py
eis1600/dates/date_patterns.py
eis1600/dates/month_methods.py
eis1600/gazetteers/Onomastics.py
eis1600/gazetteers/Spellings.py
eis1600/gazetteers/Toponyms.py
eis1600/gazetteers/__init__.py
eis1600/gazetteers/data/__init__.py
eis1600/gazetteers/data/days_gazetteer.csv
eis1600/gazetteers/data/months_gazetteer.csv
eis1600/gazetteers/data/onomastic_gazetteer.csv
eis1600/gazetteers/data/spelling_gazetteer.csv
eis1600/gazetteers/data/toponyms_gazetteer.csv
eis1600/gazetteers/data/years_gazetteer.csv
eis1600/helper/CheckFileEndingActions.py
eis1600/helper/Singleton.py
eis1600/helper/__init__.py
eis1600/helper/ar_normalization.py
eis1600/helper/chunking.py
eis1600/helper/files_sizes.py
eis1600/helper/fix_dataframe.py
eis1600/helper/logging.py
eis1600/helper/miu_random_revisions.py
eis1600/helper/parse_range.py
eis1600/helper/part_file_names.py
eis1600/helper/data/__init__.py
eis1600/json_to_text/__init__.py
eis1600/json_to_text/reconstruct.py
eis1600/json_to_tsv/__init__.py
eis1600/json_to_tsv/corpus_dump.py
eis1600/markdown/EntityTags.py
eis1600/markdown/__init__.py
eis1600/markdown/category.py
eis1600/markdown/markdown_methods.py
eis1600/markdown/markdown_patterns.py
eis1600/markdown/data/__init__.py
eis1600/markdown/data/entity_tags.csv
eis1600/miu/HeadingTracker.py
eis1600/miu/__init__.py
eis1600/model_evaluations/EvalResultsEncoder.py
eis1600/model_evaluations/__init__.py
eis1600/model_evaluations/eval_date_model.py
eis1600/model_evaluations/eval_topo_cat_model.py
eis1600-1.7.4.dist-info/LICENSE
eis1600-1.7.4.dist-info/METADATA
eis1600-1.7.4.dist-info/WHEEL
eis1600-1.7.4.dist-info/entry_points.txt
eis1600-1.7.4.dist-info/top_level.txt
eis1600-1.7.4.dist-info/RECORD
