Metadata-Version: 2.1
Name: eis1600
Version: 1.7.4
Summary: EIS1600 project tools and utilities
Home-page: https://github.com/EIS1600/eis1600-pkg
Author: Lisa Mischer
Author-email: mischer.lisa@gmail.com
License: MIT License
Classifier: Programming Language :: Python :: 3
Classifier: License :: OSI Approved :: MIT License
Classifier: Operating System :: OS Independent
Classifier: Development Status :: 1 - Planning
Classifier: Intended Audience :: Science/Research
Requires-Python: >=3.7
License-File: LICENSE
Requires-Dist: openiti
Requires-Dist: pandas
Requires-Dist: numpy
Requires-Dist: tqdm
Requires-Dist: p-tqdm
Requires-Dist: importlib-resources
Requires-Dist: jsonpickle
Requires-Dist: requests
Requires-Dist: ujson
Provides-Extra: eis
Requires-Dist: camel-tools ; extra == 'eis'
Requires-Dist: torch ; extra == 'eis'
Requires-Dist: torchvision ; extra == 'eis'
Requires-Dist: torchaudio ; extra == 'eis'
Requires-Dist: transformers ; extra == 'eis'
Provides-Extra: eval
Requires-Dist: evaluate ; extra == 'eval'
Requires-Dist: seqeval ; extra == 'eval'
Requires-Dist: tensorflow ; extra == 'eval'
Provides-Extra: ner
Requires-Dist: camel-tools ; extra == 'ner'
Requires-Dist: torch ; extra == 'ner'
